djpress_example_plugin/__init__.py
djpress_example_plugin/plugin.py
djpress_example_plugin-2.0.0.dist-info/METADATA
djpress_example_plugin-2.0.0.dist-info/WHEEL
djpress_example_plugin-2.0.0.dist-info/RECORD
