Metadata-Version: 2.4
Name: djpress-example-plugin
Version: 2.0.0
Summary: Example plugin for DJ Press
Author-email: Stuart Maxwell <stuart@amanzi.nz>
Requires-Python: >=3.9
Requires-Dist: djpress>=0.20.0
